odoo/addons/agreement_fsm/README.rst
odoo/addons/agreement_fsm/__init__.py
odoo/addons/agreement_fsm/__manifest__.py
odoo/addons/agreement_fsm/i18n/agreement_fsm.pot
odoo/addons/agreement_fsm/models/__init__.py
odoo/addons/agreement_fsm/models/agreement.py
odoo/addons/agreement_fsm/models/fsm_order.py
odoo/addons/agreement_fsm/readme/CONFIGURE.rst
odoo/addons/agreement_fsm/readme/CONTRIBUTORS.rst
odoo/addons/agreement_fsm/readme/CREDITS.rst
odoo/addons/agreement_fsm/readme/DESCRIPTION.rst
odoo/addons/agreement_fsm/readme/ROADMAP.rst
odoo/addons/agreement_fsm/readme/USAGE.rst
odoo/addons/agreement_fsm/static/description/icon.png
odoo/addons/agreement_fsm/static/description/index.html
odoo/addons/agreement_fsm/views/agreement_view.xml
odoo/addons/agreement_fsm/views/fsm_order_view.xml
odoo11_addon_agreement_fsm-11.0.1.0.0.99.dev2.dist-info/METADATA
odoo11_addon_agreement_fsm-11.0.1.0.0.99.dev2.dist-info/RECORD
odoo11_addon_agreement_fsm-11.0.1.0.0.99.dev2.dist-info/WHEEL
odoo11_addon_agreement_fsm-11.0.1.0.0.99.dev2.dist-info/top_level.txt
